hktoll/__init__.py
hktoll/_version.py
hktoll/cli.py
hktoll/datasets.py
hktoll/engine.py
hktoll/geo.py
hktoll/schemas.py
hktoll/server.py
hktoll/adapters/hk.py
hktoll/resources/urls.json
hktoll/resources/vehicle_classes.json
hktoll-0.1.1.dist-info/METADATA
hktoll-0.1.1.dist-info/WHEEL
hktoll-0.1.1.dist-info/entry_points.txt
hktoll-0.1.1.dist-info/licenses/LICENSE
hktoll-0.1.1.dist-info/RECORD
