Metadata-Version: 2.4
Name: hktoll
Version: 0.1.1
Summary: Python library & CLI to compute Hong Kong (HKeToll) tolls from official datasets
Project-URL: Homepage, https://github.com/mfarahani1998/hktoll
Project-URL: Documentation, https://github.com/mfarahani1998/hktoll#readme
Project-URL: Source, https://github.com/mfarahani1998/hktoll
Project-URL: Issues, https://github.com/mfarahani1998/hktoll/issues
Project-URL: Changelog, https://github.com/mfarahani1998/hktoll/releases
Author-email: Maverick Farahani <m.darestani98@gmail.com>
License: MIT
License-File: LICENSE
Keywords: HKeToll,bridges,gis,hk,hong kong,hong-kong,road pricing,routing,toll,tolls,transport,tunnels
Classifier: Environment :: Console
Classifier: Intended Audience :: Developers
Classifier: License :: OSI Approved :: MIT License
Classifier: Natural Language :: English
Classifier: Programming Language :: Python :: 3
Classifier: Topic :: Scientific/Engineering :: GIS
Classifier: Topic :: Software Development :: Libraries
Requires-Python: >=3.9
Requires-Dist: fastapi>=0.110
Requires-Dist: httpx>=0.27
Requires-Dist: pandas>=2.0
Requires-Dist: platformdirs>=4.0
Requires-Dist: pydantic>=2.7
Requires-Dist: shapely>=2.0
Requires-Dist: typer>=0.9
Requires-Dist: uvicorn>=0.23
Provides-Extra: dev
Requires-Dist: build>=1.2; extra == 'dev'
Requires-Dist: mypy>=1.7; extra == 'dev'
Requires-Dist: pytest-cov>=4.1; extra == 'dev'
Requires-Dist: pytest>=8.0; extra == 'dev'
Requires-Dist: ruff>=0.5.0; extra == 'dev'
Requires-Dist: types-requests; extra == 'dev'
